goupil-1.3.2.dist-info/RECORD
goupil-1.3.2.dist-info/WHEEL
goupil-1.3.2.dist-info/COPYING.LESSER
goupil-1.3.2.dist-info/COPYING
goupil-1.3.2.dist-info/top_level.txt
goupil-1.3.2.dist-info/METADATA
goupil/goupil.abi3.so
goupil/__init__.py
goupil/__main__.py
goupil/data/elements/absorption/Gd.txt
goupil/data/elements/absorption/Pm.txt
goupil/data/elements/absorption/Re.txt
goupil/data/elements/absorption/In.txt
goupil/data/elements/absorption/Ge.txt
goupil/data/elements/absorption/Sb.txt
goupil/data/elements/absorption/Sc.txt
goupil/data/elements/absorption/Po.txt
goupil/data/elements/absorption/Kr.txt
goupil/data/elements/absorption/Dy.txt
goupil/data/elements/absorption/Ru.txt
goupil/data/elements/absorption/Rb.txt
goupil/data/elements/absorption/Ga.txt
goupil/data/elements/absorption/Fe.txt
goupil/data/elements/absorption/Fr.txt
goupil/data/elements/absorption/Sr.txt
goupil/data/elements/absorption/Ra.txt
goupil/data/elements/absorption/Se.txt
goupil/data/elements/absorption/Ho.txt
goupil/data/elements/absorption/Bk.txt
goupil/data/elements/absorption/Co.txt
goupil/data/elements/absorption/Ag.txt
goupil/data/elements/absorption/Xe.txt
goupil/data/elements/absorption/La.txt
goupil/data/elements/absorption/Ni.txt
goupil/data/elements/absorption/K.txt
goupil/data/elements/absorption/Cl.txt
goupil/data/elements/absorption/As.txt
goupil/data/elements/absorption/I.txt
goupil/data/elements/absorption/Mg.txt
goupil/data/elements/absorption/Zn.txt
goupil/data/elements/absorption/Yb.txt
goupil/data/elements/absorption/Te.txt
goupil/data/elements/absorption/Lu.txt
goupil/data/elements/absorption/H.txt
goupil/data/elements/absorption/Bi.txt
goupil/data/elements/absorption/Ar.txt
goupil/data/elements/absorption/Cm.txt
goupil/data/elements/absorption/Ta.txt
goupil/data/elements/absorption/O.txt
goupil/data/elements/absorption/Au.txt
goupil/data/elements/absorption/Tc.txt
goupil/data/elements/absorption/Tb.txt
goupil/data/elements/absorption/Y.txt
goupil/data/elements/absorption/At.txt
goupil/data/elements/absorption/N.txt
goupil/data/elements/absorption/Ac.txt
goupil/data/elements/absorption/C.txt
