Metadata-Version: 2.1
Name: goupil
Version: 1.3.2
Summary: A Monte Carlo engine for the backward transport of low energy gamma-rays.
Author-email: Valentin Niess <valentin.niess@gmail.com>
License: LGPLv3
Project-URL: source, https://github.com/niess/goupil
Keywords: gamma rays,Monte Carlo,backward
Classifier: Intended Audience :: Science/Research
Classifier: Topic :: Scientific/Engineering :: Physics
Requires-Python: >=3.7.0
License-File: COPYING
License-File: COPYING.LESSER
Requires-Dist: numpy >=1.6.0
